lightweight_versioned_gitlab_pages/__init__.py
lightweight_versioned_gitlab_pages/generate.py
lightweight_versioned_gitlab_pages/version.py
lightweight_versioned_gitlab_pages/templates/index.html
lightweight_versioned_gitlab_pages-0.3.2.dist-info/LICENSE
lightweight_versioned_gitlab_pages-0.3.2.dist-info/METADATA
lightweight_versioned_gitlab_pages-0.3.2.dist-info/WHEEL
lightweight_versioned_gitlab_pages-0.3.2.dist-info/entry_points.txt
lightweight_versioned_gitlab_pages-0.3.2.dist-info/top_level.txt
lightweight_versioned_gitlab_pages-0.3.2.dist-info/RECORD
