Metadata-Version: 2.1
Name: lightweight-versioned-gitlab-pages
Version: 0.3.2
Summary: Enable GitLab pages to provide documentation for multiple versions
Home-page: https://gitlab.com/brainelectronics/lightweight-versioned-gitlab-pages
Author: brainelectronics
Author-email: jonas@brainelectronics.de
Project-URL: Bug Reports, https://gitlab.com/brainelectronics/lightweight-versioned-gitlab-pages/-/issues
Project-URL: Source, https://gitlab.com/brainelectronics/lightweight-versioned-gitlab-pages/
Keywords: gitlab,version,pages,versioning,generator,documentation
Classifier: Development Status :: 5 - Production/Stable
Classifier: Intended Audience :: Developers
Classifier: Topic :: Software Development :: Build Tools
Classifier: License :: OSI Approved :: MIT License
Classifier: Programming Language :: Python :: 3
Classifier: Programming Language :: Python :: 3.7
Classifier: Programming Language :: Python :: 3.8
Classifier: Programming Language :: Python :: 3.9
Classifier: Programming Language :: Python :: 3.10
Classifier: Programming Language :: Python :: 3 :: Only
Requires-Python: >=3.7, <4
License-File: LICENSE
Requires-Dist: python-gitlab (<4,>=3)
Requires-Dist: jinja2 (<4,>=3.1.0)
Provides-Extra: dev
Requires-Dist: tox (<4,>=3.25.1) ; extra == 'dev'
Provides-Extra: test
Requires-Dist: flake8 (<6,>=5.0.0) ; extra == 'test'
Requires-Dist: mypy (<1,>=0.991) ; extra == 'test'
Requires-Dist: coverage (<7,>=6.4.2) ; extra == 'test'
Requires-Dist: nose2 (<1,>=0.12.0) ; extra == 'test'
